negoce_ct_datamanagement/__init__.py
negoce_ct_datamanagement/adapters/__init__.py
negoce_ct_datamanagement/adapters/json/__init__.py
negoce_ct_datamanagement/adapters/json/statics.py
negoce_ct_datamanagement/adapters/json/timeseries.py
negoce_ct_datamanagement/adapters/pandas/__init__.py
negoce_ct_datamanagement/adapters/pandas/statics.py
negoce_ct_datamanagement/adapters/pandas/timeseries.py
negoce_ct_datamanagement/db_utils/__init__.py
negoce_ct_datamanagement/db_utils/connection.py
negoce_ct_datamanagement/models/__init__.py
negoce_ct_datamanagement/models/statics.py
negoce_ct_datamanagement/models/timeseries.py
negoce_ct_datamanagement/providers/__init__.py
negoce_ct_datamanagement/providers/belvis/__init__.py
negoce_ct_datamanagement/providers/belvis/_config.py
negoce_ct_datamanagement/providers/belvis/_sample_auth_session.py
negoce_ct_datamanagement/providers/belvis/imbalance.py
negoce_ct_datamanagement/providers/belvis/meteocontrol.py
negoce_ct_datamanagement/providers/belvis/requests_utils.py
negoce_ct_datamanagement/providers/belvis/uic.py
negoce_ct_datamanagement/providers/meteocontrol/__init__.py
negoce_ct_datamanagement/providers/meteocontrol/_config.py
negoce_ct_datamanagement/providers/meteocontrol/forecast.py
negoce_ct_datamanagement/providers/meteocontrol/measurements.py
negoce_ct_datamanagement/providers/meteocontrol/sites.py
negoce_ct_datamanagement/providers/meteocontrol/test_requests.py
negoce_ct_datamanagement/providers/meteocontrol/test_utils.py
negoce_ct_datamanagement/providers/meteosuisse/__init__.py
negoce_ct_datamanagement/providers/meteosuisse/_config.py
negoce_ct_datamanagement/providers/meteosuisse/radiation.py
negoce_ct_datamanagement/providers/ofev/__init__.py
negoce_ct_datamanagement/providers/ofev/_config.py
negoce_ct_datamanagement/providers/ofev/queries.py
negoce_ct_datamanagement/providers/sig_negoce/__init__.py
negoce_ct_datamanagement/providers/sig_negoce/capa_evacuation_seujet.py
negoce_ct_datamanagement-0.0.12.dist-info/METADATA
negoce_ct_datamanagement-0.0.12.dist-info/WHEEL
negoce_ct_datamanagement-0.0.12.dist-info/top_level.txt
negoce_ct_datamanagement-0.0.12.dist-info/RECORD
