Metadata-Version: 2.4
Name: negoce_ct_datamanagement
Version: 0.0.12
Summary: Package to handle Negoce CT data
Author-email: Antoine Leboube <antoine.leboube@sig-ge.ch>, Bernard Huynh <bernard.huynh@sig-ge.ch>
Project-URL: Homepage, https://github.com/sig-negoce/negoce-ct-datamanagement
Project-URL: Issues, https://github.com/sig-negoce/negoce-ct-datamanagement/issues
Classifier: Programming Language :: Python :: 3
Classifier: Operating System :: OS Independent
Requires-Python: >=3.12
Requires-Dist: numpy
Requires-Dist: openpyxl
Requires-Dist: pandas
Requires-Dist: psycopg[binary,pool]
Requires-Dist: pydantic
Requires-Dist: python-dotenv
Requires-Dist: requests
Requires-Dist: matplotlib
Requires-Dist: httpx
Requires-Dist: xlrd
Requires-Dist: fastapi
Requires-Dist: uvicorn
